vondr/__init__.py
vondr/_client.py
vondr/_images.py
vondr/_sync_client.py
vondr/exceptions.py
vondr/models.py
vondr-0.2.3.dist-info/LICENSE
vondr-0.2.3.dist-info/METADATA
vondr-0.2.3.dist-info/WHEEL
vondr-0.2.3.dist-info/RECORD
