Metadata-Version: 2.3
Name: vondr
Version: 0.2.3
Summary: Python client for the Vondr AI Platform.
License: MIT
Author: Your Name
Author-email: you@example.com
Requires-Python: >=3.10,<4.0
Classifier: License :: OSI Approved :: MIT License
Classifier: Programming Language :: Python :: 3
Classifier: Programming Language :: Python :: 3.10
Classifier: Programming Language :: Python :: 3.11
Classifier: Programming Language :: Python :: 3.12
Classifier: Programming Language :: Python :: 3.13
Requires-Dist: Pillow (>=10.0)
Requires-Dist: httpx (>=0.27,<1.0.0)
